alpaka/__init__.py
alpaka/cli.py
alpaka/core.py
alpaka/encoding.py
alpaka/enigma.py
alpaka/extraction.py
alpaka/heckel_diff.py
alpaka/obfuscation.py
alpaka_re-0.2.1.dist-info/entry_points.txt
alpaka_re-0.2.1.dist-info/licenses/LICENSE
alpaka_re-0.2.1.dist-info/WHEEL
alpaka_re-0.2.1.dist-info/METADATA
alpaka_re-0.2.1.dist-info/RECORD
