Metadata-Version: 2.4
Name: alpaka-re
Version: 0.2.1
Summary: A tool for mapping classes between different versions of the same APK.
Keywords: apk,android,mapping,reverse-engineering,deobfuscation
Author-email: Daniel Firer <danielfirefire@gmail.com>
Requires-Python: >=3.7
Classifier: Programming Language :: Python :: 3
Classifier: Programming Language :: Python :: 3.7
Classifier: Programming Language :: Python :: 3.8
Classifier: Programming Language :: Python :: 3.9
Classifier: Programming Language :: Python :: 3.10
Classifier: Programming Language :: Python :: 3.11
Classifier: Programming Language :: Python :: 3.12
Classifier: License :: OSI Approved :: MIT License
Classifier: Operating System :: OS Independent
Classifier: Topic :: Software Development :: Libraries :: Python Modules
Classifier: Topic :: Security
License-File: LICENSE
Requires-Dist: click
Requires-Dist: lief
Project-URL: Bug Tracker, https://github.com/DanielFi/alpaka/issues
Project-URL: Homepage, https://github.com/DanielFi/alpaka
Project-URL: Repository, https://github.com/DanielFi/alpaka
